impersonate/__init__.py
impersonate/impersonate.py
impersonate-0.1.0.dist-info/LICENSE
impersonate-0.1.0.dist-info/METADATA
impersonate-0.1.0.dist-info/WHEEL
impersonate-0.1.0.dist-info/top_level.txt
impersonate-0.1.0.dist-info/RECORD
