Metadata-Version: 2.1
Name: impersonate
Version: 0.1.0
Summary: In progress
Home-page: https://github.com/synthient/impersonate
Author: benjamin
Author-email: benjamin@synthient.com
License: MIT license
Keywords: impersonate
Classifier: Development Status :: 2 - Pre-Alpha
Classifier: Intended Audience :: Developers
Classifier: License :: OSI Approved :: MIT License
Classifier: Natural Language :: English
Classifier: Programming Language :: Python :: 3
Classifier: Programming Language :: Python :: 3.6
Classifier: Programming Language :: Python :: 3.7
Classifier: Programming Language :: Python :: 3.8
Requires-Python: >=3.6
License-File: LICENSE
